[{"NOMBRE":"AMERICANO - Sanatorio Americano S.A.","WEB":"http://www.seguroamericano.com.uy","ARTIGAS":"FALSE","CANELONES":"FALSE","CERRO_LARGO":"FALSE","COLONIA":"FALSE","DURAZNO":"FALSE","FLORES":"FALSE","FLORIDA":"FALSE","LAVALLEJA":"FALSE","MALDONADO":"FALSE","MONTEVIDEO":"TRUE","PAYSANDU":"FALSE","RIO_NEGRO":"FALSE","RIVERA":"FALSE","ROCHA":"FALSE","SALTO":"FALSE","SAN_JOSE":"FALSE","SORIANO":"FALSE","TACUAREMBO":"FALSE","TREINTA_Y_TRES":"FALSE","META_NINOS":"53.5%","META_EMBARAZADAS":"100.0%","META_ADOLESCENTE":"11.3%","META_ADULTO":"42.3%","META_ADULTO_MAYOR":"44.4%","MEDICAMENTOS_GENERAL":"150","MEDICAMENTOS_GENERAL_FONASA":"135","MEDICAMENTOS_TOPEADOS":"83","MEDICAMENTOS_TOPEADOS_FONASA":"83","CONSULTA_GENERAL":"s/d","CONSULTA_GENERAL_FONASA":"s/d","CONSULTA_PEDIATRIA":"s/d","CONSULTA_PEDIATRIA_FONASA":"s/d","CONTROL_EMBARAZO":"s/d","CONTROL_EMBARAZO_FONASA":"s/d","CONSULTA_GINECOLOGIA":"s/d","CONSULTA_GINECOLOGIA_FONASA":"s/d","CONSULT_OTR_ESP":"s/d","CONSULT_OTR_ESP_FONASA":"s/d","CONSULTA_NO_URG_DOM":"s/d","CONSULTA_NO_URG_DOM_FONASA":"s/d","CONS_ODONT":"s/d","CONS_ODONT_FONASA":"s/d","CONS_MED_REF":"s/d","CONS_MED_REF_FONASA":"s/d","CONS_URG_CENTRALIZADA":"s/d","CONS_URG_CENTRALIZADA_FONASA":"s/d","CONS_URG_DOM":"s/d","CONS_URG_DOM_FONASA":"s/d","ESTUDIO_ENDOSCOPIA":"s/d","ESTUDIO_ENDOSCOPIA_FONASA":"s/d","ESTUDIO_ECOGRAFIA_SIMPLE":"s/d","ESTUDIO_ECOGRAFIA_SIMPLE_FONASA":"s/d","ESTUDIO_ECOGRAFIA_OBS":"s/d","ESTUDIO_ECOGRAFIA_OBS_FONASA":"s/d","ESTUDIO_ECODOPPLER":"s/d","ESTUDIO_ECODOPPLER_FONASA":"s/d","ESTUDIO_IMAGEN_ABDOMEN":"s/d","ESTUDIO_IMAGEN_ABDOMEN_FONASA":"s/d","ESTUDIO_IMAGEN_TORAX":"s/d","ESTUDIO_IMAGEN_TORAX_FONASA":"s/d","ESTUDIO_IMAGEN_COLORECTAL":"s/d","ESTUDIO_IMAGEN_COLORECTAL_FONASA":"s/d","ESTUDIO_RESONANCIA":"s/d","ESTUDIO_RESONANCIA_FONASA":"s/d","ESTUDIO_TOMOGRAFIA":"s/d","ESTUDIO_TOMOGRAFIA_FONASA":"s/d","ESTUDIO_LABORATORIO":"s/d","ESTUDIO_LABORATORIO_FONASA":"s/d","TIEMPO_ESP_MED_GEN":"0.29","TIEMPO_ESP_PEDIATRIA":"2.1","TIEMPO_ESP_CIRUG":"s/d","TIEMPO_ESP_GIN":"0.63","ENT_QUEJAS":"66%","ENT_DERECHOS":"67%","PERSONAL_CANT_MED":"s/d","PERSONAL_CANT_GIN":"s/d","PERSONAL_CANT_PED":"s/d","PERSONAL_CANT_ENF":"s/d","PERSONAL_CANT_LICENF":"s/d","CITAS_PERSONAL":"TRUE","CITAS_TELEFONICA":"TRUE","CITAS_WEB":"FALSE","RECORDATORIO_TELEFONO":"FALSE","RECORDATORIO_SMS":"FALSE","RECORDATORIO_CORREO":"FALSE","INCOMPLETA":"TRUE","COSTO":{"MEDICAMENTOS":112,"CONSULTAS_NO_URGENTES":"s/d","CONSULTAS_URGENTES":"s/d","ESTUDIOS_Y_LABORATORIOS":"s/d"},"METAS":{"NINOS":"53.5%","EMBARAZADAS":"100.0%","ADOLESCENTE":"11.3%","ADULTO":"42.3%","ADULTO_MAYOR":"44.4%"},"TIEMPOS_ESPERA":{"MEDICINA_GENERAL":"0.29","PEDIATRIA":"2.1","CIRUGIA_GENERAL":"s/d","GINECOLOGIA":"0.63"},"SATISFACCION":{"QUEJAS":"66%","DERECHOS":"67%"},"PERSONAL":{"MEDICOS":"s/d","GINECOLOGOS":"s/d","PEDIATRAS":"s/d","ENFERMEROS":"s/d","LICENFER":"s/d"}},{"NOMBRE":"BLUE CROSS - Blue Cross & Blue ShielD","WEB":"http://www.bcbsu.com.uy","ARTIGAS":"FALSE","CANELONES":"FALSE","CERRO_LARGO":"FALSE","COLONIA":"FALSE","DURAZNO":"FALSE","FLORES":"FALSE","FLORIDA":"FALSE","LAVALLEJA":"FALSE","MALDONADO":"FALSE","MONTEVIDEO":"TRUE","PAYSANDU":"FALSE","RIO_NEGRO":"FALSE","RIVERA":"FALSE","ROCHA":"FALSE","SALTO":"FALSE","SAN_JOSE":"FALSE","SORIANO":"FALSE","TACUAREMBO":"FALSE","TREINTA_Y_TRES":"FALSE","META_NINOS":"100.0%","META_EMBARAZADAS":"100.0%","META_ADOLESCENTE":"19.3%","META_ADULTO":"21.1%","META_ADULTO_MAYOR":"0.0%","MEDICAMENTOS_GENERAL":"150","MEDICAMENTOS_GENERAL_FONASA":"77","MEDICAMENTOS_TOPEADOS":"83","MEDICAMENTOS_TOPEADOS_FONASA":"s/d","CONSULTA_GENERAL":"s/d","CONSULTA_GENERAL_FONASA":"s/d","CONSULTA_PEDIATRIA":"s/d","CONSULTA_PEDIATRIA_FONASA":"s/d","CONTROL_EMBARAZO":"s/d","CONTROL_EMBARAZO_FONASA":"s/d","CONSULTA_GINECOLOGIA":"s/d","CONSULTA_GINECOLOGIA_FONASA":"s/d","CONSULT_OTR_ESP":"s/d","CONSULT_OTR_ESP_FONASA":"s/d","CONSULTA_NO_URG_DOM":"s/d","CONSULTA_NO_URG_DOM_FONASA":"s/d","CONS_ODONT":"s/d","CONS_ODONT_FONASA":"s/d","CONS_MED_REF":"s/d","CONS_MED_REF_FONASA":"s/d","CONS_URG_CENTRALIZADA":"s/d","CONS_URG_CENTRALIZADA_FONASA":"s/d","CONS_URG_DOM":"s/d","CONS_URG_DOM_FONASA":"s/d","ESTUDIO_ENDOSCOPIA":"s/d","ESTUDIO_ENDOSCOPIA_FONASA":"s/d","ESTUDIO_ECOGRAFIA_SIMPLE":"s/d","ESTUDIO_ECOGRAFIA_SIMPLE_FONASA":"s/d","ESTUDIO_ECOGRAFIA_OBS":"s/d","ESTUDIO_ECOGRAFIA_OBS_FONASA":"s/d","ESTUDIO_ECODOPPLER":"s/d","ESTUDIO_ECODOPPLER_FONASA":"s/d","ESTUDIO_IMAGEN_ABDOMEN":"s/d","ESTUDIO_IMAGEN_ABDOMEN_FONASA":"s/d","ESTUDIO_IMAGEN_TORAX":"s/d","ESTUDIO_IMAGEN_TORAX_FONASA":"s/d","ESTUDIO_IMAGEN_COLORECTAL":"s/d","ESTUDIO_IMAGEN_COLORECTAL_FONASA":"s/d","ESTUDIO_RESONANCIA":"s/d","ESTUDIO_RESONANCIA_FONASA":"s/d","ESTUDIO_TOMOGRAFIA":"s/d","ESTUDIO_TOMOGRAFIA_FONASA":"s/d","ESTUDIO_LABORATORIO":"s/d","ESTUDIO_LABORATORIO_FONASA":"s/d","TIEMPO_ESP_MED_GEN":"0.73","TIEMPO_ESP_PEDIATRIA":"0.58","TIEMPO_ESP_CIRUG":"0.79","TIEMPO_ESP_GIN":"0.19","ENT_QUEJAS":"81%","ENT_DERECHOS":"35%","PERSONAL_CANT_MED":"s/d","PERSONAL_CANT_GIN":"s/d","PERSONAL_CANT_PED":"s/d","PERSONAL_CANT_ENF":"s/d","PERSONAL_CANT_LICENF":"s/d","CITAS_PERSONAL":"TRUE","CITAS_TELEFONICA":"TRUE","CITAS_WEB":"TRUE","RECORDATORIO_TELEFONO":"FALSE","RECORDATORIO_SMS":"TRUE","RECORDATORIO_CORREO":"FALSE","INCOMPLETA":"TRUE","COSTO":{"MEDICAMENTOS":"s/d","CONSULTAS_NO_URGENTES":"s/d","CONSULTAS_URGENTES":"s/d","ESTUDIOS_Y_LABORATORIOS":"s/d"},"METAS":{"NINOS":"100.0%","EMBARAZADAS":"100.0%","ADOLESCENTE":"19.3%","ADULTO":"21.1%","ADULTO_MAYOR":"0.0%"},"TIEMPOS_ESPERA":{"MEDICINA_GENERAL":"0.73","PEDIATRIA":"0.58","CIRUGIA_GENERAL":"0.79","GINECOLOGIA":"0.19"},"SATISFACCION":{"QUEJAS":"81%","DERECHOS":"35%"},"PERSONAL":{"MEDICOS":"s/d","GINECOLOGOS":"s/d","PEDIATRAS":"s/d","ENFERMEROS":"s/d","LICENFER":"s/d"}},{"NOMBRE":"BRITÁNICO - La Sociedad Hospital Británico en el Uruguay","WEB":"www.hospitalbritanico.com.uy","ARTIGAS":"FALSE","CANELONES":"FALSE","CERRO_LARGO":"FALSE","COLONIA":"FALSE","DURAZNO":"FALSE","FLORES":"FALSE","FLORIDA":"FALSE","LAVALLEJA":"FALSE","MALDONADO":"FALSE","MONTEVIDEO":"TRUE","PAYSANDU":"FALSE","RIO_NEGRO":"FALSE","RIVERA":"FALSE","ROCHA":"FALSE","SALTO":"FALSE","SAN_JOSE":"FALSE","SORIANO":"FALSE","TACUAREMBO":"FALSE","TREINTA_Y_TRES":"FALSE","META_NINOS":"7.8%","META_EMBARAZADAS":"42.8%","META_ADOLESCENTE":"1.4%","META_ADULTO":"24.0%","META_ADULTO_MAYOR":"65.5%","MEDICAMENTOS_GENERAL":"150","MEDICAMENTOS_GENERAL_FONASA":"171","MEDICAMENTOS_TOPEADOS":"83","MEDICAMENTOS_TOPEADOS_FONASA":"s/d","CONSULTA_GENERAL":"s/d","CONSULTA_GENERAL_FONASA":"s/d","CONSULTA_PEDIATRIA":"s/d","CONSULTA_PEDIATRIA_FONASA":"s/d","CONTROL_EMBARAZO":"s/d","CONTROL_EMBARAZO_FONASA":"s/d","CONSULTA_GINECOLOGIA":"s/d","CONSULTA_GINECOLOGIA_FONASA":"s/d","CONSULT_OTR_ESP":"s/d","CONSULT_OTR_ESP_FONASA":"s/d","CONSULTA_NO_URG_DOM":"s/d","CONSULTA_NO_URG_DOM_FONASA":"s/d","CONS_ODONT":"s/d","CONS_ODONT_FONASA":"s/d","CONS_MED_REF":"s/d","CONS_MED_REF_FONASA":"s/d","CONS_URG_CENTRALIZADA":"s/d","CONS_URG_CENTRALIZADA_FONASA":"s/d","CONS_URG_DOM":"s/d","CONS_URG_DOM_FONASA":"s/d","ESTUDIO_ENDOSCOPIA":"s/d","ESTUDIO_ENDOSCOPIA_FONASA":"s/d","ESTUDIO_ECOGRAFIA_SIMPLE":"s/d","ESTUDIO_ECOGRAFIA_SIMPLE_FONASA":"s/d","ESTUDIO_ECOGRAFIA_OBS":"s/d","ESTUDIO_ECOGRAFIA_OBS_FONASA":"s/d","ESTUDIO_ECODOPPLER":"s/d","ESTUDIO_ECODOPPLER_FONASA":"s/d","ESTUDIO_IMAGEN_ABDOMEN":"s/d","ESTUDIO_IMAGEN_ABDOMEN_FONASA":"s/d","ESTUDIO_IMAGEN_TORAX":"s/d","ESTUDIO_IMAGEN_TORAX_FONASA":"s/d","ESTUDIO_IMAGEN_COLORECTAL":"s/d","ESTUDIO_IMAGEN_COLORECTAL_FONASA":"s/d","ESTUDIO_RESONANCIA":"s/d","ESTUDIO_RESONANCIA_FONASA":"s/d","ESTUDIO_TOMOGRAFIA":"s/d","ESTUDIO_TOMOGRAFIA_FONASA":"s/d","ESTUDIO_LABORATORIO":"s/d","ESTUDIO_LABORATORIO_FONASA":"s/d","TIEMPO_ESP_MED_GEN":"0.09","TIEMPO_ESP_PEDIATRIA":"0.12","TIEMPO_ESP_CIRUG":"0.36","TIEMPO_ESP_GIN":"0.16","ENT_QUEJAS":"69%","ENT_DERECHOS":"35%","PERSONAL_CANT_MED":"3,6","PERSONAL_CANT_GIN":"s/d","PERSONAL_CANT_PED":"26,6","PERSONAL_CANT_ENF":"25,7","PERSONAL_CANT_LICENF":"8,8","CITAS_PERSONAL":"TRUE","CITAS_TELEFONICA":"TRUE","CITAS_WEB":"TRUE","RECORDATORIO_TELEFONO":"FALSE","RECORDATORIO_SMS":"TRUE","RECORDATORIO_CORREO":"TRUE","INCOMPLETA":"TRUE","COSTO":{"MEDICAMENTOS":"s/d","CONSULTAS_NO_URGENTES":"s/d","CONSULTAS_URGENTES":"s/d","ESTUDIOS_Y_LABORATORIOS":"s/d"},"METAS":{"NINOS":"7.8%","EMBARAZADAS":"42.8%","ADOLESCENTE":"1.4%","ADULTO":"24.0%","ADULTO_MAYOR":"65.5%"},"TIEMPOS_ESPERA":{"MEDICINA_GENERAL":"0.09","PEDIATRIA":"0.12","CIRUGIA_GENERAL":"0.36","GINECOLOGIA":"0.16"},"SATISFACCION":{"QUEJAS":"69%","DERECHOS":"35%"},"PERSONAL":{"MEDICOS":"3,6","GINECOLOGOS":"s/d","PEDIATRAS":"26,6","ENFERMEROS":"25,7","LICENFER":"8,8"}},{"NOMBRE":"CASA DE GALICIA - Casa de Galicia","WEB":"http://www.casadegalicia.org.uy","ARTIGAS":"FALSE","CANELONES":"TRUE","CERRO_LARGO":"FALSE","COLONIA":"FALSE","DURAZNO":"FALSE","FLORES":"FALSE","FLORIDA":"FALSE","LAVALLEJA":"FALSE","MALDONADO":"FALSE","MONTEVIDEO":"TRUE","PAYSANDU":"FALSE","RIO_NEGRO":"FALSE","RIVERA":"FALSE","ROCHA":"FALSE","SALTO":"FALSE","SAN_JOSE":"FALSE","SORIANO":"FALSE","TACUAREMBO":"FALSE","TREINTA_Y_TRES":"FALSE","META_NINOS":"99.3%","META_EMBARAZADAS":"98.5%","META_ADOLESCENTE":"27.1%","META_ADULTO":"45.4%","META_ADULTO_MAYOR":"58.4%","MEDICAMENTOS_GENERAL":"165","MEDICAMENTOS_GENERAL_FONASA":"108","MEDICAMENTOS_TOPEADOS":"83","MEDICAMENTOS_TOPEADOS_FONASA":"83","CONSULTA_GENERAL":"75","CONSULTA_GENERAL_FONASA":"75","CONSULTA_PEDIATRIA":"75","CONSULTA_PEDIATRIA_FONASA":"75","CONTROL_EMBARAZO":"75","CONTROL_EMBARAZO_FONASA":"75","CONSULTA_GINECOLOGIA":"75","CONSULTA_GINECOLOGIA_FONASA":"75","CONSULT_OTR_ESP":"189","CONSULT_OTR_ESP_FONASA":"189","CONSULTA_NO_URG_DOM":"335","CONSULTA_NO_URG_DOM_FONASA":"307","CONS_ODONT":"307","CONS_ODONT_FONASA":"307","CONS_MED_REF":"75","CONS_MED_REF_FONASA":"75","CONS_URG_CENTRALIZADA":"75","CONS_URG_CENTRALIZADA_FONASA":"335","CONS_URG_DOM":"462","CONS_URG_DOM_FONASA":"462","ESTUDIO_ENDOSCOPIA":"476","ESTUDIO_ENDOSCOPIA_FONASA":"476","ESTUDIO_ECOGRAFIA_SIMPLE":"382","ESTUDIO_ECOGRAFIA_SIMPLE_FONASA":"382","ESTUDIO_ECOGRAFIA_OBS":"476","ESTUDIO_ECOGRAFIA_OBS_FONASA":"476","ESTUDIO_ECODOPPLER":"1164","ESTUDIO_ECODOPPLER_FONASA":"1164","ESTUDIO_IMAGEN_ABDOMEN":"306","ESTUDIO_IMAGEN_ABDOMEN_FONASA":"306","ESTUDIO_IMAGEN_TORAX":"306","ESTUDIO_IMAGEN_TORAX_FONASA":"306","ESTUDIO_IMAGEN_COLORECTAL":"756","ESTUDIO_IMAGEN_COLORECTAL_FONASA":"756","ESTUDIO_RESONANCIA":"1164","ESTUDIO_RESONANCIA_FONASA":"1164","ESTUDIO_TOMOGRAFIA":"784","ESTUDIO_TOMOGRAFIA_FONASA":"784","ESTUDIO_LABORATORIO":"687","ESTUDIO_LABORATORIO_FONASA":"687","TIEMPO_ESP_MED_GEN":"0.4","TIEMPO_ESP_PEDIATRIA":"1","TIEMPO_ESP_CIRUG":"0.93","TIEMPO_ESP_GIN":"3","ENT_QUEJAS":"76%","ENT_DERECHOS":"35%","PERSONAL_CANT_MED":"15","PERSONAL_CANT_GIN":"9,4","PERSONAL_CANT_PED":"26,1","PERSONAL_CANT_ENF":"6,1","PERSONAL_CANT_LICENF":"0,2","CITAS_PERSONAL":"TRUE","CITAS_TELEFONICA":"TRUE","CITAS_WEB":"FALSE","RECORDATORIO_TELEFONO":"FALSE","RECORDATORIO_SMS":"FALSE","RECORDATORIO_CORREO":"FALSE","INCOMPLETA":"FALSE","COSTO":{"MEDICAMENTOS":109,"CONSULTAS_NO_URGENTES":149,"CONSULTAS_URGENTES":333,"ESTUDIOS_Y_LABORATORIOS":541},"METAS":{"NINOS":"99.3%","EMBARAZADAS":"98.5%","ADOLESCENTE":"27.1%","ADULTO":"45.4%","ADULTO_MAYOR":"58.4%"},"TIEMPOS_ESPERA":{"MEDICINA_GENERAL":"0.4","PEDIATRIA":"1","CIRUGIA_GENERAL":"0.93","GINECOLOGIA":"3"},"SATISFACCION":{"QUEJAS":"76%","DERECHOS":"35%"},"PERSONAL":{"MEDICOS":"15","GINECOLOGOS":"9,4","PEDIATRAS":"26,1","ENFERMEROS":"6,1","LICENFER":"0,2"}},{"NOMBRE":"CASMU-IAMPP - Institución de Asistencia Médica Privada de Profesionales sin fines de lucro","WEB":"http://www.casmu.com.uy","ARTIGAS":"FALSE","CANELONES":"TRUE","CERRO_LARGO":"FALSE","COLONIA":"FALSE","DURAZNO":"FALSE","FLORES":"FALSE","FLORIDA":"FALSE","LAVALLEJA":"FALSE","MALDONADO":"TRUE","MONTEVIDEO":"TRUE","PAYSANDU":"FALSE","RIO_NEGRO":"FALSE","RIVERA":"FALSE","ROCHA":"FALSE","SALTO":"FALSE","SAN_JOSE":"TRUE","SORIANO":"FALSE","TACUAREMBO":"FALSE","TREINTA_Y_TRES":"FALSE","META_NINOS":"92.5%","META_EMBARAZADAS":"99.0%","META_ADOLESCENTE":"32.0%","META_ADULTO":"44.0%","META_ADULTO_MAYOR":"59.6%","MEDICAMENTOS_GENERAL":"183","MEDICAMENTOS_GENERAL_FONASA":"147","MEDICAMENTOS_TOPEADOS":"83","MEDICAMENTOS_TOPEADOS_FONASA":"83","CONSULTA_GENERAL":"75","CONSULTA_GENERAL_FONASA":"75","CONSULTA_PEDIATRIA":"75","CONSULTA_PEDIATRIA_FONASA":"75","CONTROL_EMBARAZO":"75","CONTROL_EMBARAZO_FONASA":"75","CONSULTA_GINECOLOGIA":"78","CONSULTA_GINECOLOGIA_FONASA":"78","CONSULT_OTR_ESP":"196","CONSULT_OTR_ESP_FONASA":"196","CONSULTA_NO_URG_DOM":"321","CONSULTA_NO_URG_DOM_FONASA":"321","CONS_ODONT":"321","CONS_ODONT_FONASA":"321","CONS_MED_REF":"75","CONS_MED_REF_FONASA":"75","CONS_URG_CENTRALIZADA":"75","CONS_URG_CENTRALIZADA_FONASA":"321","CONS_URG_DOM":"465","CONS_URG_DOM_FONASA":"465","ESTUDIO_ENDOSCOPIA":"476","ESTUDIO_ENDOSCOPIA_FONASA":"476","ESTUDIO_ECOGRAFIA_SIMPLE":"341","ESTUDIO_ECOGRAFIA_SIMPLE_FONASA":"341","ESTUDIO_ECOGRAFIA_OBS":"476","ESTUDIO_ECOGRAFIA_OBS_FONASA":"476","ESTUDIO_ECODOPPLER":"741","ESTUDIO_ECODOPPLER_FONASA":"741","ESTUDIO_IMAGEN_ABDOMEN":"341","ESTUDIO_IMAGEN_ABDOMEN_FONASA":"341","ESTUDIO_IMAGEN_TORAX":"341","ESTUDIO_IMAGEN_TORAX_FONASA":"341","ESTUDIO_IMAGEN_COLORECTAL":"476","ESTUDIO_IMAGEN_COLORECTAL_FONASA":"476","ESTUDIO_RESONANCIA":"1164","ESTUDIO_RESONANCIA_FONASA":"1164","ESTUDIO_TOMOGRAFIA":"1164","ESTUDIO_TOMOGRAFIA_FONASA":"1164","ESTUDIO_LABORATORIO":"613","ESTUDIO_LABORATORIO_FONASA":"613","TIEMPO_ESP_MED_GEN":"s/d","TIEMPO_ESP_PEDIATRIA":"s/d","TIEMPO_ESP_CIRUG":"s/d","TIEMPO_ESP_GIN":"s/d","ENT_QUEJAS":"44%","ENT_DERECHOS":"40%","PERSONAL_CANT_MED":"23,7","PERSONAL_CANT_GIN":"6,9","PERSONAL_CANT_PED":"33,8","PERSONAL_CANT_ENF":"7,5","PERSONAL_CANT_LICENF":"1","CITAS_PERSONAL":"TRUE","CITAS_TELEFONICA":"TRUE","CITAS_WEB":"TRUE","RECORDATORIO_TELEFONO":"FALSE","RECORDATORIO_SMS":"FALSE","RECORDATORIO_CORREO":"FALSE","INCOMPLETA":"TRUE","COSTO":{"MEDICAMENTOS":124,"CONSULTAS_NO_URGENTES":152,"CONSULTAS_URGENTES":331,"ESTUDIOS_Y_LABORATORIOS":"s/d"},"METAS":{"NINOS":"92.5%","EMBARAZADAS":"99.0%","ADOLESCENTE":"32.0%","ADULTO":"44.0%","ADULTO_MAYOR":"59.6%"},"TIEMPOS_ESPERA":{"MEDICINA_GENERAL":"s/d","PEDIATRIA":"s/d","CIRUGIA_GENERAL":"s/d","GINECOLOGIA":"s/d"},"SATISFACCION":{"QUEJAS":"44%","DERECHOS":"40%"},"PERSONAL":{"MEDICOS":"23,7","GINECOLOGOS":"6,9","PEDIATRAS":"33,8","ENFERMEROS":"7,5","LICENFER":"1"}},{"NOMBRE":"CCOU - Círculo Católico de Obreros del Uruguay","WEB":"http://www.circulocatolico.com.uy","ARTIGAS":"FALSE","CANELONES":"TRUE","CERRO_LARGO":"FALSE","COLONIA":"TRUE","DURAZNO":"FALSE","FLORES":"TRUE","FLORIDA":"TRUE","LAVALLEJA":"FALSE","MALDONADO":"TRUE","MONTEVIDEO":"TRUE","PAYSANDU":"FALSE","RIO_NEGRO":"FALSE","RIVERA":"FALSE","ROCHA":"FALSE","SALTO":"FALSE","SAN_JOSE":"TRUE","SORIANO":"TRUE","TACUAREMBO":"FALSE","TREINTA_Y_TRES":"FALSE","META_NINOS":"100.0%","META_EMBARAZADAS":"100.0%","META_ADOLESCENTE":"27.6%","META_ADULTO":"44.0%","META_ADULTO_MAYOR":"58.2%","MEDICAMENTOS_GENERAL":"151","MEDICAMENTOS_GENERAL_FONASA":"183","MEDICAMENTOS_TOPEADOS":"83","MEDICAMENTOS_TOPEADOS_FONASA":"83","CONSULTA_GENERAL":"76","CONSULTA_GENERAL_FONASA":"76","CONSULTA_PEDIATRIA":"76","CONSULTA_PEDIATRIA_FONASA":"0","CONTROL_EMBARAZO":"76","CONTROL_EMBARAZO_FONASA":"76","CONSULTA_GINECOLOGIA":"78","CONSULTA_GINECOLOGIA_FONASA":"78","CONSULT_OTR_ESP":"222","CONSULT_OTR_ESP_FONASA":"222","CONSULTA_NO_URG_DOM":"275","CONSULTA_NO_URG_DOM_FONASA":"313","CONS_ODONT":"0","CONS_ODONT_FONASA":"0","CONS_MED_REF":"76","CONS_MED_REF_FONASA":"76","CONS_URG_CENTRALIZADA":"76","CONS_URG_CENTRALIZADA_FONASA":"275","CONS_URG_DOM":"435","CONS_URG_DOM_FONASA":"435","ESTUDIO_ENDOSCOPIA":"448","ESTUDIO_ENDOSCOPIA_FONASA":"448","ESTUDIO_ECOGRAFIA_SIMPLE":"448","ESTUDIO_ECOGRAFIA_SIMPLE_FONASA":"448","ESTUDIO_ECOGRAFIA_OBS":"448","ESTUDIO_ECOGRAFIA_OBS_FONASA":"448","ESTUDIO_ECODOPPLER":"1030","ESTUDIO_ECODOPPLER_FONASA":"1030","ESTUDIO_IMAGEN_ABDOMEN":"286","ESTUDIO_IMAGEN_ABDOMEN_FONASA":"286","ESTUDIO_IMAGEN_TORAX":"286","ESTUDIO_IMAGEN_TORAX_FONASA":"286","ESTUDIO_IMAGEN_COLORECTAL":"286","ESTUDIO_IMAGEN_COLORECTAL_FONASA":"286","ESTUDIO_RESONANCIA":"1164","ESTUDIO_RESONANCIA_FONASA":"1164","ESTUDIO_TOMOGRAFIA":"1030","ESTUDIO_TOMOGRAFIA_FONASA":"1030","ESTUDIO_LABORATORIO":"573","ESTUDIO_LABORATORIO_FONASA":"288","TIEMPO_ESP_MED_GEN":"0.01","TIEMPO_ESP_PEDIATRIA":"0.03","TIEMPO_ESP_CIRUG":"0.1","TIEMPO_ESP_GIN":"0.1","ENT_QUEJAS":"54%","ENT_DERECHOS":"35%","PERSONAL_CANT_MED":"25,5","PERSONAL_CANT_GIN":"12,5","PERSONAL_CANT_PED":"23,9","PERSONAL_CANT_ENF":"21,2","PERSONAL_CANT_LICENF":"0,8","CITAS_PERSONAL":"TRUE","CITAS_TELEFONICA":"TRUE","CITAS_WEB":"TRUE","RECORDATORIO_TELEFONO":"FALSE","RECORDATORIO_SMS":"TRUE","RECORDATORIO_CORREO":"FALSE","INCOMPLETA":"FALSE","COSTO":{"MEDICAMENTOS":125,"CONSULTAS_NO_URGENTES":107,"CONSULTAS_URGENTES":305,"ESTUDIOS_Y_LABORATORIOS":488},"METAS":{"NINOS":"100.0%","EMBARAZADAS":"100.0%","ADOLESCENTE":"27.6%","ADULTO":"44.0%","ADULTO_MAYOR":"58.2%"},"TIEMPOS_ESPERA":{"MEDICINA_GENERAL":"0.01","PEDIATRIA":"0.03","CIRUGIA_GENERAL":"0.1","GINECOLOGIA":"0.1"},"SATISFACCION":{"QUEJAS":"54%","DERECHOS":"35%"},"PERSONAL":{"MEDICOS":"25,5","GINECOLOGOS":"12,5","PEDIATRAS":"23,9","ENFERMEROS":"21,2","LICENFER":"0,8"}},{"NOMBRE":"COSEM - Cooperativa de Servicios Médicos","WEB":"http://www.cosem.com.uy","ARTIGAS":"FALSE","CANELONES":"TRUE","CERRO_LARGO":"FALSE","COLONIA":"FALSE","DURAZNO":"FALSE","FLORES":"FALSE","FLORIDA":"FALSE","LAVALLEJA":"FALSE","MALDONADO":"FALSE","MONTEVIDEO":"TRUE","PAYSANDU":"FALSE","RIO_NEGRO":"FALSE","RIVERA":"FALSE","ROCHA":"FALSE","SALTO":"FALSE","SAN_JOSE":"FALSE","SORIANO":"FALSE","TACUAREMBO":"FALSE","TREINTA_Y_TRES":"FALSE","META_NINOS":"93.5%","META_EMBARAZADAS":"99.3%","META_ADOLESCENTE":"23.3%","META_ADULTO":"44.2%","META_ADULTO_MAYOR":"58.2%","MEDICAMENTOS_GENERAL":"176","MEDICAMENTOS_GENERAL_FONASA":"124","MEDICAMENTOS_TOPEADOS":"83","MEDICAMENTOS_TOPEADOS_FONASA":"83","CONSULTA_GENERAL":"75","CONSULTA_GENERAL_FONASA":"75","CONSULTA_PEDIATRIA":"75","CONSULTA_PEDIATRIA_FONASA":"75","CONTROL_EMBARAZO":"75","CONTROL_EMBARAZO_FONASA":"75","CONSULTA_GINECOLOGIA":"77","CONSULTA_GINECOLOGIA_FONASA":"77","CONSULT_OTR_ESP":"227","CONSULT_OTR_ESP_FONASA":"227","CONSULTA_NO_URG_DOM":"105","CONSULTA_NO_URG_DOM_FONASA":"256","CONS_ODONT":"353","CONS_ODONT_FONASA":"353","CONS_MED_REF":"0","CONS_MED_REF_FONASA":"0","CONS_URG_CENTRALIZADA":"75","CONS_URG_CENTRALIZADA_FONASA":"105","CONS_URG_DOM":"304","CONS_URG_DOM_FONASA":"304","ESTUDIO_ENDOSCOPIA":"563","ESTUDIO_ENDOSCOPIA_FONASA":"563","ESTUDIO_ECOGRAFIA_SIMPLE":"286","ESTUDIO_ECOGRAFIA_SIMPLE_FONASA":"286","ESTUDIO_ECOGRAFIA_OBS":"288","ESTUDIO_ECOGRAFIA_OBS_FONASA":"288","ESTUDIO_ECODOPPLER":"563","ESTUDIO_ECODOPPLER_FONASA":"563","ESTUDIO_IMAGEN_ABDOMEN":"272","ESTUDIO_IMAGEN_ABDOMEN_FONASA":"272","ESTUDIO_IMAGEN_TORAX":"272","ESTUDIO_IMAGEN_TORAX_FONASA":"272","ESTUDIO_IMAGEN_COLORECTAL":"563","ESTUDIO_IMAGEN_COLORECTAL_FONASA":"563","ESTUDIO_RESONANCIA":"1164","ESTUDIO_RESONANCIA_FONASA":"1164","ESTUDIO_TOMOGRAFIA":"1035","ESTUDIO_TOMOGRAFIA_FONASA":"1035","ESTUDIO_LABORATORIO":"1110","ESTUDIO_LABORATORIO_FONASA":"1110","TIEMPO_ESP_MED_GEN":"1.45","TIEMPO_ESP_PEDIATRIA":"0.95","TIEMPO_ESP_CIRUG":"2.5","TIEMPO_ESP_GIN":"0.66","ENT_QUEJAS":"67%","ENT_DERECHOS":"70%","PERSONAL_CANT_MED":"4","PERSONAL_CANT_GIN":"10,9","PERSONAL_CANT_PED":"31,2","PERSONAL_CANT_ENF":"12","PERSONAL_CANT_LICENF":"1,5","CITAS_PERSONAL":"TRUE","CITAS_TELEFONICA":"TRUE","CITAS_WEB":"TRUE","RECORDATORIO_TELEFONO":"FALSE","RECORDATORIO_SMS":"TRUE","RECORDATORIO_CORREO":"TRUE","INCOMPLETA":"FALSE","COSTO":{"MEDICAMENTOS":116,"CONSULTAS_NO_URGENTES":132,"CONSULTAS_URGENTES":197,"ESTUDIOS_Y_LABORATORIOS":509},"METAS":{"NINOS":"93.5%","EMBARAZADAS":"99.3%","ADOLESCENTE":"23.3%","ADULTO":"44.2%","ADULTO_MAYOR":"58.2%"},"TIEMPOS_ESPERA":{"MEDICINA_GENERAL":"1.45","PEDIATRIA":"0.95","CIRUGIA_GENERAL":"2.5","GINECOLOGIA":"0.66"},"SATISFACCION":{"QUEJAS":"67%","DERECHOS":"70%"},"PERSONAL":{"MEDICOS":"4","GINECOLOGOS":"10,9","PEDIATRAS":"31,2","ENFERMEROS":"12","LICENFER":"1,5"}},{"NOMBRE":"CUDAM - Centro Uruguayo de Asistencia Médica","WEB":"http://www.cudam.com.uy","ARTIGAS":"FALSE","CANELONES":"FALSE","CERRO_LARGO":"FALSE","COLONIA":"FALSE","DURAZNO":"FALSE","FLORES":"FALSE","FLORIDA":"FALSE","LAVALLEJA":"FALSE","MALDONADO":"FALSE","MONTEVIDEO":"TRUE","PAYSANDU":"FALSE","RIO_NEGRO":"FALSE","RIVERA":"FALSE","ROCHA":"FALSE","SALTO":"FALSE","SAN_JOSE":"FALSE","SORIANO":"FALSE","TACUAREMBO":"FALSE","TREINTA_Y_TRES":"FALSE","META_NINOS":"92.3%","META_EMBARAZADAS":"99.5%","META_ADOLESCENTE":"30.1%","META_ADULTO":"50.1%","META_ADULTO_MAYOR":"59.4%","MEDICAMENTOS_GENERAL":"130","MEDICAMENTOS_GENERAL_FONASA":"137","MEDICAMENTOS_TOPEADOS":"75","MEDICAMENTOS_TOPEADOS_FONASA":"75","CONSULTA_GENERAL":"66","CONSULTA_GENERAL_FONASA":"0","CONSULTA_PEDIATRIA":"0","CONSULTA_PEDIATRIA_FONASA":"0","CONTROL_EMBARAZO":"66","CONTROL_EMBARAZO_FONASA":"0","CONSULTA_GINECOLOGIA":"66","CONSULTA_GINECOLOGIA_FONASA":"0","CONSULT_OTR_ESP":"132","CONSULT_OTR_ESP_FONASA":"0","CONSULTA_NO_URG_DOM":"132","CONSULTA_NO_URG_DOM_FONASA":"0","CONS_ODONT":"158","CONS_ODONT_FONASA":"0","CONS_MED_REF":"66","CONS_MED_REF_FONASA":"66","CONS_URG_CENTRALIZADA":"66","CONS_URG_CENTRALIZADA_FONASA":"0","CONS_URG_DOM":"260","CONS_URG_DOM_FONASA":"0","ESTUDIO_ENDOSCOPIA":"386","ESTUDIO_ENDOSCOPIA_FONASA":"386","ESTUDIO_ECOGRAFIA_SIMPLE":"267","ESTUDIO_ECOGRAFIA_SIMPLE_FONASA":"267","ESTUDIO_ECOGRAFIA_OBS":"267","ESTUDIO_ECOGRAFIA_OBS_FONASA":"267","ESTUDIO_ECODOPPLER":"190","ESTUDIO_ECODOPPLER_FONASA":"64","ESTUDIO_IMAGEN_ABDOMEN":"169","ESTUDIO_IMAGEN_ABDOMEN_FONASA":"64","ESTUDIO_IMAGEN_TORAX":"169","ESTUDIO_IMAGEN_TORAX_FONASA":"64","ESTUDIO_IMAGEN_COLORECTAL":"190","ESTUDIO_IMAGEN_COLORECTAL_FONASA":"64","ESTUDIO_RESONANCIA":"1164","ESTUDIO_RESONANCIA_FONASA":"1164","ESTUDIO_TOMOGRAFIA":"647","ESTUDIO_TOMOGRAFIA_FONASA":"647","ESTUDIO_LABORATORIO":"339","ESTUDIO_LABORATORIO_FONASA":"339","TIEMPO_ESP_MED_GEN":"0.05","TIEMPO_ESP_PEDIATRIA":"3.89","TIEMPO_ESP_CIRUG":"3.48","TIEMPO_ESP_GIN":"0.1","ENT_QUEJAS":"37%","ENT_DERECHOS":"14%","PERSONAL_CANT_MED":"8,2","PERSONAL_CANT_GIN":"6,4","PERSONAL_CANT_PED":"15","PERSONAL_CANT_ENF":"1,1","PERSONAL_CANT_LICENF":"0","CITAS_PERSONAL":"TRUE","CITAS_TELEFONICA":"TRUE","CITAS_WEB":"FALSE","RECORDATORIO_TELEFONO":"FALSE","RECORDATORIO_SMS":"TRUE","RECORDATORIO_CORREO":"FALSE","INCOMPLETA":"FALSE","COSTO":{"MEDICAMENTOS":104,"CONSULTAS_NO_URGENTES":47,"CONSULTAS_URGENTES":81,"ESTUDIOS_Y_LABORATORIOS":296},"METAS":{"NINOS":"92.3%","EMBARAZADAS":"99.5%","ADOLESCENTE":"30.1%","ADULTO":"50.1%","ADULTO_MAYOR":"59.4%"},"TIEMPOS_ESPERA":{"MEDICINA_GENERAL":"0.05","PEDIATRIA":"3.89","CIRUGIA_GENERAL":"3.48","GINECOLOGIA":"0.1"},"SATISFACCION":{"QUEJAS":"37%","DERECHOS":"14%"},"PERSONAL":{"MEDICOS":"8,2","GINECOLOGOS":"6,4","PEDIATRAS":"15","ENFERMEROS":"1,1","LICENFER":"0"}},{"NOMBRE":"ESPAÑOLA - Asociación Española Primera de Socorros Mutuos","WEB":"http://www.asesp.com.uy","ARTIGAS":"FALSE","CANELONES":"FALSE","CERRO_LARGO":"FALSE","COLONIA":"FALSE","DURAZNO":"FALSE","FLORES":"FALSE","FLORIDA":"FALSE","LAVALLEJA":"FALSE","MALDONADO":"FALSE","MONTEVIDEO":"TRUE","PAYSANDU":"FALSE","RIO_NEGRO":"FALSE","RIVERA":"FALSE","ROCHA":"FALSE","SALTO":"FALSE","SAN_JOSE":"FALSE","SORIANO":"FALSE","TACUAREMBO":"FALSE","TREINTA_Y_TRES":"FALSE","META_NINOS":"94.3%","META_EMBARAZADAS":"98.3%","META_ADOLESCENTE":"44.8%","META_ADULTO":"44.8%","META_ADULTO_MAYOR":"59.6%","MEDICAMENTOS_GENERAL":"179","MEDICAMENTOS_GENERAL_FONASA":"122","MEDICAMENTOS_TOPEADOS":"83","MEDICAMENTOS_TOPEADOS_FONASA":"83","CONSULTA_GENERAL":"75","CONSULTA_GENERAL_FONASA":"75","CONSULTA_PEDIATRIA":"0","CONSULTA_PEDIATRIA_FONASA":"0","CONTROL_EMBARAZO":"75","CONTROL_EMBARAZO_FONASA":"75","CONSULTA_GINECOLOGIA":"77","CONSULTA_GINECOLOGIA_FONASA":"77","CONSULT_OTR_ESP":"188","CONSULT_OTR_ESP_FONASA":"188","CONSULTA_NO_URG_DOM":"488","CONSULTA_NO_URG_DOM_FONASA":"365","CONS_ODONT":"365","CONS_ODONT_FONASA":"365","CONS_MED_REF":"75","CONS_MED_REF_FONASA":"75","CONS_URG_CENTRALIZADA":"75","CONS_URG_CENTRALIZADA_FONASA":"488","CONS_URG_DOM":"488","CONS_URG_DOM_FONASA":"488","ESTUDIO_ENDOSCOPIA":"764","ESTUDIO_ENDOSCOPIA_FONASA":"764","ESTUDIO_ECOGRAFIA_SIMPLE":"460","ESTUDIO_ECOGRAFIA_SIMPLE_FONASA":"460","ESTUDIO_ECOGRAFIA_OBS":"460","ESTUDIO_ECOGRAFIA_OBS_FONASA":"460","ESTUDIO_ECODOPPLER":"722","ESTUDIO_ECODOPPLER_FONASA":"722","ESTUDIO_IMAGEN_ABDOMEN":"308","ESTUDIO_IMAGEN_ABDOMEN_FONASA":"308","ESTUDIO_IMAGEN_TORAX":"308","ESTUDIO_IMAGEN_TORAX_FONASA":"308","ESTUDIO_IMAGEN_COLORECTAL":"308","ESTUDIO_IMAGEN_COLORECTAL_FONASA":"308","ESTUDIO_RESONANCIA":"1164","ESTUDIO_RESONANCIA_FONASA":"1164","ESTUDIO_TOMOGRAFIA":"936","ESTUDIO_TOMOGRAFIA_FONASA":"936","ESTUDIO_LABORATORIO":"666","ESTUDIO_LABORATORIO_FONASA":"666","TIEMPO_ESP_MED_GEN":"0.03","TIEMPO_ESP_PEDIATRIA":"0.17","TIEMPO_ESP_CIRUG":"0.26","TIEMPO_ESP_GIN":"0.14","ENT_QUEJAS":"58%","ENT_DERECHOS":"66%","PERSONAL_CANT_MED":"23,7","PERSONAL_CANT_GIN":"10,3","PERSONAL_CANT_PED":"31,5","PERSONAL_CANT_ENF":"16,6","PERSONAL_CANT_LICENF":"1,1","CITAS_PERSONAL":"TRUE","CITAS_TELEFONICA":"TRUE","CITAS_WEB":"TRUE","RECORDATORIO_TELEFONO":"FALSE","RECORDATORIO_SMS":"FALSE","RECORDATORIO_CORREO":"FALSE","INCOMPLETA":"FALSE","COSTO":{"MEDICAMENTOS":116,"CONSULTAS_NO_URGENTES":160,"CONSULTAS_URGENTES":384,"ESTUDIOS_Y_LABORATORIOS":508},"METAS":{"NINOS":"94.3%","EMBARAZADAS":"98.3%","ADOLESCENTE":"44.8%","ADULTO":"44.8%","ADULTO_MAYOR":"59.6%"},"TIEMPOS_ESPERA":{"MEDICINA_GENERAL":"0.03","PEDIATRIA":"0.17","CIRUGIA_GENERAL":"0.26","GINECOLOGIA":"0.14"},"SATISFACCION":{"QUEJAS":"58%","DERECHOS":"66%"},"PERSONAL":{"MEDICOS":"23,7","GINECOLOGOS":"10,3","PEDIATRAS":"31,5","ENFERMEROS":"16,6","LICENFER":"1,1"}},{"NOMBRE":"Mutualista Hospital Evangélico","WEB":"http://www.hospitalevangelico.com.uy","ARTIGAS":"FALSE","CANELONES":"TRUE","CERRO_LARGO":"FALSE","COLONIA":"TRUE","DURAZNO":"FALSE","FLORES":"FALSE","FLORIDA":"TRUE","LAVALLEJA":"FALSE","MALDONADO":"FALSE","MONTEVIDEO":"TRUE","PAYSANDU":"FALSE","RIO_NEGRO":"FALSE","RIVERA":"FALSE","ROCHA":"FALSE","SALTO":"FALSE","SAN_JOSE":"TRUE","SORIANO":"TRUE","TACUAREMBO":"FALSE","TREINTA_Y_TRES":"FALSE","META_NINOS":"96.3%","META_EMBARAZADAS":"98.5%","META_ADOLESCENTE":"25.9%","META_ADULTO":"44.3%","META_ADULTO_MAYOR":"58.5%","MEDICAMENTOS_GENERAL":"155","MEDICAMENTOS_GENERAL_FONASA":"179","MEDICAMENTOS_TOPEADOS":"83","MEDICAMENTOS_TOPEADOS_FONASA":"83","CONSULTA_GENERAL":"75","CONSULTA_GENERAL_FONASA":"75","CONSULTA_PEDIATRIA":"75","CONSULTA_PEDIATRIA_FONASA":"75","CONTROL_EMBARAZO":"75","CONTROL_EMBARAZO_FONASA":"75","CONSULTA_GINECOLOGIA":"77","CONSULTA_GINECOLOGIA_FONASA":"77","CONSULT_OTR_ESP":"169","CONSULT_OTR_ESP_FONASA":"169","CONSULTA_NO_URG_DOM":"219","CONSULTA_NO_URG_DOM_FONASA":"308","CONS_ODONT":"219","CONS_ODONT_FONASA":"219","CONS_MED_REF":"75","CONS_MED_REF_FONASA":"75","CONS_URG_CENTRALIZADA":"75","CONS_URG_CENTRALIZADA_FONASA":"219","CONS_URG_DOM":"361","CONS_URG_DOM_FONASA":"361","ESTUDIO_ENDOSCOPIA":"405","ESTUDIO_ENDOSCOPIA_FONASA":"405","ESTUDIO_ECOGRAFIA_SIMPLE":"395","ESTUDIO_ECOGRAFIA_SIMPLE_FONASA":"395","ESTUDIO_ECOGRAFIA_OBS":"395","ESTUDIO_ECOGRAFIA_OBS_FONASA":"395","ESTUDIO_ECODOPPLER":"672","ESTUDIO_ECODOPPLER_FONASA":"672","ESTUDIO_IMAGEN_ABDOMEN":"286","ESTUDIO_IMAGEN_ABDOMEN_FONASA":"286","ESTUDIO_IMAGEN_TORAX":"286","ESTUDIO_IMAGEN_TORAX_FONASA":"286","ESTUDIO_IMAGEN_COLORECTAL":"286","ESTUDIO_IMAGEN_COLORECTAL_FONASA":"286","ESTUDIO_RESONANCIA":"1164","ESTUDIO_RESONANCIA_FONASA":"1164","ESTUDIO_TOMOGRAFIA":"672","ESTUDIO_TOMOGRAFIA_FONASA":"672","ESTUDIO_LABORATORIO":"519","ESTUDIO_LABORATORIO_FONASA":"519","TIEMPO_ESP_MED_GEN":"0.3","TIEMPO_ESP_PEDIATRIA":"0.43","TIEMPO_ESP_CIRUG":"0.93","TIEMPO_ESP_GIN":"0.36","ENT_QUEJAS":"60%","ENT_DERECHOS":"35%","PERSONAL_CANT_MED":"17","PERSONAL_CANT_GIN":"10,1","PERSONAL_CANT_PED":"18,2","PERSONAL_CANT_ENF":"12,4","PERSONAL_CANT_LICENF":"1,3","CITAS_PERSONAL":"TRUE","CITAS_TELEFONICA":"TRUE","CITAS_WEB":"FALSE","RECORDATORIO_TELEFONO":"FALSE","RECORDATORIO_SMS":"TRUE","RECORDATORIO_CORREO":"FALSE","INCOMPLETA":"FALSE","COSTO":{"MEDICAMENTOS":125,"CONSULTAS_NO_URGENTES":128,"CONSULTAS_URGENTES":254,"ESTUDIOS_Y_LABORATORIOS":423},"METAS":{"NINOS":"96.3%","EMBARAZADAS":"98.5%","ADOLESCENTE":"25.9%","ADULTO":"44.3%","ADULTO_MAYOR":"58.5%"},"TIEMPOS_ESPERA":{"MEDICINA_GENERAL":"0.3","PEDIATRIA":"0.43","CIRUGIA_GENERAL":"0.93","GINECOLOGIA":"0.36"},"SATISFACCION":{"QUEJAS":"60%","DERECHOS":"35%"},"PERSONAL":{"MEDICOS":"17","GINECOLOGOS":"10,1","PEDIATRAS":"18,2","ENFERMEROS":"12,4","LICENFER":"1,3"}},{"NOMBRE":"GREMCA - Gremial Médica Centro Asistencial","WEB":"http://www.gremca.com.uy","ARTIGAS":"FALSE","CANELONES":"TRUE","CERRO_LARGO":"FALSE","COLONIA":"FALSE","DURAZNO":"FALSE","FLORES":"FALSE","FLORIDA":"FALSE","LAVALLEJA":"FALSE","MALDONADO":"FALSE","MONTEVIDEO":"TRUE","PAYSANDU":"FALSE","RIO_NEGRO":"FALSE","RIVERA":"FALSE","ROCHA":"FALSE","SALTO":"FALSE","SAN_JOSE":"TRUE","SORIANO":"FALSE","TACUAREMBO":"FALSE","TREINTA_Y_TRES":"FALSE","META_NINOS":"94.5%","META_EMBARAZADAS":"99.3%","META_ADOLESCENTE":"56.2%","META_ADULTO":"49.2%","META_ADULTO_MAYOR":"63.2%","MEDICAMENTOS_GENERAL":"147","MEDICAMENTOS_GENERAL_FONASA":"155","MEDICAMENTOS_TOPEADOS":"82","MEDICAMENTOS_TOPEADOS_FONASA":"82","CONSULTA_GENERAL":"69","CONSULTA_GENERAL_FONASA":"0","CONSULTA_PEDIATRIA":"0","CONSULTA_PEDIATRIA_FONASA":"0","CONTROL_EMBARAZO":"69","CONTROL_EMBARAZO_FONASA":"0","CONSULTA_GINECOLOGIA":"69","CONSULTA_GINECOLOGIA_FONASA":"0","CONSULT_OTR_ESP":"191","CONSULT_OTR_ESP_FONASA":"0","CONSULTA_NO_URG_DOM":"191","CONSULTA_NO_URG_DOM_FONASA":"0","CONS_ODONT":"191","CONS_ODONT_FONASA":"0","CONS_MED_REF":"69","CONS_MED_REF_FONASA":"0","CONS_URG_CENTRALIZADA":"69","CONS_URG_CENTRALIZADA_FONASA":"0","CONS_URG_DOM":"389","CONS_URG_DOM_FONASA":"182","ESTUDIO_ENDOSCOPIA":"383","ESTUDIO_ENDOSCOPIA_FONASA":"383","ESTUDIO_ECOGRAFIA_SIMPLE":"383","ESTUDIO_ECOGRAFIA_SIMPLE_FONASA":"383","ESTUDIO_ECOGRAFIA_OBS":"383","ESTUDIO_ECOGRAFIA_OBS_FONASA":"383","ESTUDIO_ECODOPPLER":"383","ESTUDIO_ECODOPPLER_FONASA":"383","ESTUDIO_IMAGEN_ABDOMEN":"197","ESTUDIO_IMAGEN_ABDOMEN_FONASA":"197","ESTUDIO_IMAGEN_TORAX":"197","ESTUDIO_IMAGEN_TORAX_FONASA":"197","ESTUDIO_IMAGEN_COLORECTAL":"197","ESTUDIO_IMAGEN_COLORECTAL_FONASA":"197","ESTUDIO_RESONANCIA":"1164","ESTUDIO_RESONANCIA_FONASA":"1164","ESTUDIO_TOMOGRAFIA":"383","ESTUDIO_TOMOGRAFIA_FONASA":"383","ESTUDIO_LABORATORIO":"704","ESTUDIO_LABORATORIO_FONASA":"704","TIEMPO_ESP_MED_GEN":"1.15","TIEMPO_ESP_PEDIATRIA":"1.4","TIEMPO_ESP_CIRUG":"2.67","TIEMPO_ESP_GIN":"3.06","ENT_QUEJAS":"54%","ENT_DERECHOS":"38%","PERSONAL_CANT_MED":"12,6","PERSONAL_CANT_GIN":"9,2","PERSONAL_CANT_PED":"13,5","PERSONAL_CANT_ENF":"7,1","PERSONAL_CANT_LICENF":"0","CITAS_PERSONAL":"TRUE","CITAS_TELEFONICA":"TRUE","CITAS_WEB":"FALSE","RECORDATORIO_TELEFONO":"FALSE","RECORDATORIO_SMS":"FALSE","RECORDATORIO_CORREO":"FALSE","INCOMPLETA":"FALSE","COSTO":{"MEDICAMENTOS":116,"CONSULTAS_NO_URGENTES":53,"CONSULTAS_URGENTES":160,"ESTUDIOS_Y_LABORATORIOS":364},"METAS":{"NINOS":"94.5%","EMBARAZADAS":"99.3%","ADOLESCENTE":"56.2%","ADULTO":"49.2%","ADULTO_MAYOR":"63.2%"},"TIEMPOS_ESPERA":{"MEDICINA_GENERAL":"1.15","PEDIATRIA":"1.4","CIRUGIA_GENERAL":"2.67","GINECOLOGIA":"3.06"},"SATISFACCION":{"QUEJAS":"54%","DERECHOS":"38%"},"PERSONAL":{"MEDICOS":"12,6","GINECOLOGOS":"9,2","PEDIATRAS":"13,5","ENFERMEROS":"7,1","LICENFER":"0"}},{"NOMBRE":"MEDICARE - Copamhi Asociación Civil ","WEB":"http://www.medicare.com.uy","ARTIGAS":"FALSE","CANELONES":"FALSE","CERRO_LARGO":"FALSE","COLONIA":"FALSE","DURAZNO":"FALSE","FLORES":"FALSE","FLORIDA":"FALSE","LAVALLEJA":"FALSE","MALDONADO":"FALSE","MONTEVIDEO":"TRUE","PAYSANDU":"FALSE","RIO_NEGRO":"FALSE","RIVERA":"FALSE","ROCHA":"FALSE","SALTO":"FALSE","SAN_JOSE":"FALSE","SORIANO":"FALSE","TACUAREMBO":"FALSE","TREINTA_Y_TRES":"FALSE","META_NINOS":"95.0%","META_EMBARAZADAS":"100.0%","META_ADOLESCENTE":"57.0%","META_ADULTO":"55.8%","META_ADULTO_MAYOR":"67.3%","MEDICAMENTOS_GENERAL":"150","MEDICAMENTOS_GENERAL_FONASA":"150","MEDICAMENTOS_TOPEADOS":"83","MEDICAMENTOS_TOPEADOS_FONASA":"s/d","CONSULTA_GENERAL":"s/d","CONSULTA_GENERAL_FONASA":"s/d","CONSULTA_PEDIATRIA":"s/d","CONSULTA_PEDIATRIA_FONASA":"s/d","CONTROL_EMBARAZO":"s/d","CONTROL_EMBARAZO_FONASA":"s/d","CONSULTA_GINECOLOGIA":"s/d","CONSULTA_GINECOLOGIA_FONASA":"s/d","CONSULT_OTR_ESP":"s/d","CONSULT_OTR_ESP_FONASA":"s/d","CONSULTA_NO_URG_DOM":"s/d","CONSULTA_NO_URG_DOM_FONASA":"s/d","CONS_ODONT":"s/d","CONS_ODONT_FONASA":"s/d","CONS_MED_REF":"s/d","CONS_MED_REF_FONASA":"s/d","CONS_URG_CENTRALIZADA":"s/d","CONS_URG_CENTRALIZADA_FONASA":"s/d","CONS_URG_DOM":"s/d","CONS_URG_DOM_FONASA":"s/d","ESTUDIO_ENDOSCOPIA":"s/d","ESTUDIO_ENDOSCOPIA_FONASA":"s/d","ESTUDIO_ECOGRAFIA_SIMPLE":"s/d","ESTUDIO_ECOGRAFIA_SIMPLE_FONASA":"s/d","ESTUDIO_ECOGRAFIA_OBS":"s/d","ESTUDIO_ECOGRAFIA_OBS_FONASA":"s/d","ESTUDIO_ECODOPPLER":"s/d","ESTUDIO_ECODOPPLER_FONASA":"s/d","ESTUDIO_IMAGEN_ABDOMEN":"s/d","ESTUDIO_IMAGEN_ABDOMEN_FONASA":"s/d","ESTUDIO_IMAGEN_TORAX":"s/d","ESTUDIO_IMAGEN_TORAX_FONASA":"s/d","ESTUDIO_IMAGEN_COLORECTAL":"s/d","ESTUDIO_IMAGEN_COLORECTAL_FONASA":"s/d","ESTUDIO_RESONANCIA":"s/d","ESTUDIO_RESONANCIA_FONASA":"s/d","ESTUDIO_TOMOGRAFIA":"s/d","ESTUDIO_TOMOGRAFIA_FONASA":"s/d","ESTUDIO_LABORATORIO":"s/d","ESTUDIO_LABORATORIO_FONASA":"s/d","TIEMPO_ESP_MED_GEN":"1.25","TIEMPO_ESP_PEDIATRIA":"1.65","TIEMPO_ESP_CIRUG":"2.33","TIEMPO_ESP_GIN":"0.77","ENT_QUEJAS":"71%","ENT_DERECHOS":"25%","PERSONAL_CANT_MED":"s/d","PERSONAL_CANT_GIN":"s/d","PERSONAL_CANT_PED":"s/d","PERSONAL_CANT_ENF":"s/d","PERSONAL_CANT_LICENF":"s/d","CITAS_PERSONAL":"TRUE","CITAS_TELEFONICA":"TRUE","CITAS_WEB":"FALSE","RECORDATORIO_TELEFONO":"FALSE","RECORDATORIO_SMS":"TRUE","RECORDATORIO_CORREO":"FALSE","INCOMPLETA":"TRUE","COSTO":{"MEDICAMENTOS":"s/d","CONSULTAS_NO_URGENTES":"s/d","CONSULTAS_URGENTES":"s/d","ESTUDIOS_Y_LABORATORIOS":"s/d"},"METAS":{"NINOS":"95.0%","EMBARAZADAS":"100.0%","ADOLESCENTE":"57.0%","ADULTO":"55.8%","ADULTO_MAYOR":"67.3%"},"TIEMPOS_ESPERA":{"MEDICINA_GENERAL":"1.25","PEDIATRIA":"1.65","CIRUGIA_GENERAL":"2.33","GINECOLOGIA":"0.77"},"SATISFACCION":{"QUEJAS":"71%","DERECHOS":"25%"},"PERSONAL":{"MEDICOS":"s/d","GINECOLOGOS":"s/d","PEDIATRAS":"s/d","ENFERMEROS":"s/d","LICENFER":"s/d"}},{"NOMBRE":"MP - Medicina Personalizada ","WEB":"http://www.mp.com.uy","ARTIGAS":"FALSE","CANELONES":"FALSE","CERRO_LARGO":"FALSE","COLONIA":"FALSE","DURAZNO":"FALSE","FLORES":"FALSE","FLORIDA":"FALSE","LAVALLEJA":"FALSE","MALDONADO":"FALSE","MONTEVIDEO":"TRUE","PAYSANDU":"FALSE","RIO_NEGRO":"FALSE","RIVERA":"FALSE","ROCHA":"FALSE","SALTO":"FALSE","SAN_JOSE":"FALSE","SORIANO":"FALSE","TACUAREMBO":"FALSE","TREINTA_Y_TRES":"FALSE","META_NINOS":"99.8%","META_EMBARAZADAS":"100.0%","META_ADOLESCENTE":"31.7%","META_ADULTO":"42.3%","META_ADULTO_MAYOR":"0.0%","MEDICAMENTOS_GENERAL":"150","MEDICAMENTOS_GENERAL_FONASA":"171","MEDICAMENTOS_TOPEADOS":"83","MEDICAMENTOS_TOPEADOS_FONASA":"s/d","CONSULTA_GENERAL":"s/d","CONSULTA_GENERAL_FONASA":"s/d","CONSULTA_PEDIATRIA":"s/d","CONSULTA_PEDIATRIA_FONASA":"s/d","CONTROL_EMBARAZO":"s/d","CONTROL_EMBARAZO_FONASA":"s/d","CONSULTA_GINECOLOGIA":"s/d","CONSULTA_GINECOLOGIA_FONASA":"s/d","CONSULT_OTR_ESP":"s/d","CONSULT_OTR_ESP_FONASA":"s/d","CONSULTA_NO_URG_DOM":"s/d","CONSULTA_NO_URG_DOM_FONASA":"s/d","CONS_ODONT":"s/d","CONS_ODONT_FONASA":"s/d","CONS_MED_REF":"s/d","CONS_MED_REF_FONASA":"s/d","CONS_URG_CENTRALIZADA":"s/d","CONS_URG_CENTRALIZADA_FONASA":"s/d","CONS_URG_DOM":"s/d","CONS_URG_DOM_FONASA":"s/d","ESTUDIO_ENDOSCOPIA":"s/d","ESTUDIO_ENDOSCOPIA_FONASA":"s/d","ESTUDIO_ECOGRAFIA_SIMPLE":"s/d","ESTUDIO_ECOGRAFIA_SIMPLE_FONASA":"s/d","ESTUDIO_ECOGRAFIA_OBS":"s/d","ESTUDIO_ECOGRAFIA_OBS_FONASA":"s/d","ESTUDIO_ECODOPPLER":"s/d","ESTUDIO_ECODOPPLER_FONASA":"s/d","ESTUDIO_IMAGEN_ABDOMEN":"s/d","ESTUDIO_IMAGEN_ABDOMEN_FONASA":"s/d","ESTUDIO_IMAGEN_TORAX":"s/d","ESTUDIO_IMAGEN_TORAX_FONASA":"s/d","ESTUDIO_IMAGEN_COLORECTAL":"s/d","ESTUDIO_IMAGEN_COLORECTAL_FONASA":"s/d","ESTUDIO_RESONANCIA":"s/d","ESTUDIO_RESONANCIA_FONASA":"s/d","ESTUDIO_TOMOGRAFIA":"s/d","ESTUDIO_TOMOGRAFIA_FONASA":"s/d","ESTUDIO_LABORATORIO":"s/d","ESTUDIO_LABORATORIO_FONASA":"s/d","TIEMPO_ESP_MED_GEN":"s/d","TIEMPO_ESP_PEDIATRIA":"s/d","TIEMPO_ESP_CIRUG":"s/d","TIEMPO_ESP_GIN":"s/d","ENT_QUEJAS":"76%","ENT_DERECHOS":"46%","PERSONAL_CANT_MED":"17,5","PERSONAL_CANT_GIN":"s/d","PERSONAL_CANT_PED":"s/d","PERSONAL_CANT_ENF":"1,1","PERSONAL_CANT_LICENF":"6,7","CITAS_PERSONAL":"TRUE","CITAS_TELEFONICA":"TRUE","CITAS_WEB":"TRUE","RECORDATORIO_TELEFONO":"FALSE","RECORDATORIO_SMS":"TRUE","RECORDATORIO_CORREO":"FALSE","INCOMPLETA":"TRUE","COSTO":{"MEDICAMENTOS":"s/d","CONSULTAS_NO_URGENTES":"s/d","CONSULTAS_URGENTES":"s/d","ESTUDIOS_Y_LABORATORIOS":"s/d"},"METAS":{"NINOS":"99.8%","EMBARAZADAS":"100.0%","ADOLESCENTE":"31.7%","ADULTO":"42.3%","ADULTO_MAYOR":"0.0%"},"TIEMPOS_ESPERA":{"MEDICINA_GENERAL":"s/d","PEDIATRIA":"s/d","CIRUGIA_GENERAL":"s/d","GINECOLOGIA":"s/d"},"SATISFACCION":{"QUEJAS":"76%","DERECHOS":"46%"},"PERSONAL":{"MEDICOS":"17,5","GINECOLOGOS":"s/d","PEDIATRAS":"s/d","ENFERMEROS":"1,1","LICENFER":"6,7"}},{"NOMBRE":"MUCAM - Médica Uruguaya Corporación de Asistencia Medica","WEB":"http://www.medicauruguaya.com.uy","ARTIGAS":"FALSE","CANELONES":"TRUE","CERRO_LARGO":"TRUE","COLONIA":"TRUE","DURAZNO":"TRUE","FLORES":"FALSE","FLORIDA":"TRUE","LAVALLEJA":"TRUE","MALDONADO":"TRUE","MONTEVIDEO":"TRUE","PAYSANDU":"FALSE","RIO_NEGRO":"TRUE","RIVERA":"TRUE","ROCHA":"TRUE","SALTO":"FALSE","SAN_JOSE":"TRUE","SORIANO":"TRUE","TACUAREMBO":"TRUE","TREINTA_Y_TRES":"TRUE","META_NINOS":"92.3%","META_EMBARAZADAS":"98.3%","META_ADOLESCENTE":"37.0%","META_ADULTO":"46.0%","META_ADULTO_MAYOR":"60.4%","MEDICAMENTOS_GENERAL":"171","MEDICAMENTOS_GENERAL_FONASA":"171","MEDICAMENTOS_TOPEADOS":"83","MEDICAMENTOS_TOPEADOS_FONASA":"83","CONSULTA_GENERAL":"75","CONSULTA_GENERAL_FONASA":"0","CONSULTA_PEDIATRIA":"0","CONSULTA_PEDIATRIA_FONASA":"0","CONTROL_EMBARAZO":"75","CONTROL_EMBARAZO_FONASA":"0","CONSULTA_GINECOLOGIA":"77","CONSULTA_GINECOLOGIA_FONASA":"0","CONSULT_OTR_ESP":"231","CONSULT_OTR_ESP_FONASA":"0","CONSULTA_NO_URG_DOM":"309","CONSULTA_NO_URG_DOM_FONASA":"0","CONS_ODONT":"329","CONS_ODONT_FONASA":"0","CONS_MED_REF":"75","CONS_MED_REF_FONASA":"0","CONS_URG_CENTRALIZADA":"75","CONS_URG_CENTRALIZADA_FONASA":"0","CONS_URG_DOM":"478","CONS_URG_DOM_FONASA":"0","ESTUDIO_ENDOSCOPIA":"784","ESTUDIO_ENDOSCOPIA_FONASA":"64","ESTUDIO_ECOGRAFIA_SIMPLE":"185","ESTUDIO_ECOGRAFIA_SIMPLE_FONASA":"64","ESTUDIO_ECOGRAFIA_OBS":"185","ESTUDIO_ECOGRAFIA_OBS_FONASA":"64","ESTUDIO_ECODOPPLER":"667","ESTUDIO_ECODOPPLER_FONASA":"64","ESTUDIO_IMAGEN_ABDOMEN":"305","ESTUDIO_IMAGEN_ABDOMEN_FONASA":"64","ESTUDIO_IMAGEN_TORAX":"305","ESTUDIO_IMAGEN_TORAX_FONASA":"64","ESTUDIO_IMAGEN_COLORECTAL":"305","ESTUDIO_IMAGEN_COLORECTAL_FONASA":"64","ESTUDIO_RESONANCIA":"1164","ESTUDIO_RESONANCIA_FONASA":"64","ESTUDIO_TOMOGRAFIA":"540","ESTUDIO_TOMOGRAFIA_FONASA":"64","ESTUDIO_LABORATORIO":"369","ESTUDIO_LABORATORIO_FONASA":"128","TIEMPO_ESP_MED_GEN":"0.02","TIEMPO_ESP_PEDIATRIA":"0.01","TIEMPO_ESP_CIRUG":"0.82","TIEMPO_ESP_GIN":"3","ENT_QUEJAS":"43%","ENT_DERECHOS":"19%","PERSONAL_CANT_MED":"12","PERSONAL_CANT_GIN":"12,1","PERSONAL_CANT_PED":"22,2","PERSONAL_CANT_ENF":"4,4","PERSONAL_CANT_LICENF":"0,5","CITAS_PERSONAL":"TRUE","CITAS_TELEFONICA":"TRUE","CITAS_WEB":"FALSE","RECORDATORIO_TELEFONO":"FALSE","RECORDATORIO_SMS":"FALSE","RECORDATORIO_CORREO":"FALSE","INCOMPLETA":"FALSE","COSTO":{"MEDICAMENTOS":127,"CONSULTAS_NO_URGENTES":73,"CONSULTAS_URGENTES":138,"ESTUDIOS_Y_LABORATORIOS":229},"METAS":{"NINOS":"92.3%","EMBARAZADAS":"98.3%","ADOLESCENTE":"37.0%","ADULTO":"46.0%","ADULTO_MAYOR":"60.4%"},"TIEMPOS_ESPERA":{"MEDICINA_GENERAL":"0.02","PEDIATRIA":"0.01","CIRUGIA_GENERAL":"0.82","GINECOLOGIA":"3"},"SATISFACCION":{"QUEJAS":"43%","DERECHOS":"19%"},"PERSONAL":{"MEDICOS":"12","GINECOLOGOS":"12,1","PEDIATRAS":"22,2","ENFERMEROS":"4,4","LICENFER":"0,5"}},{"NOMBRE":"Primédica S.A.","WEB":"http://www.primedica.org","ARTIGAS":"FALSE","CANELONES":"FALSE","CERRO_LARGO":"FALSE","COLONIA":"FALSE","DURAZNO":"FALSE","FLORES":"FALSE","FLORIDA":"FALSE","LAVALLEJA":"FALSE","MALDONADO":"FALSE","MONTEVIDEO":"TRUE","PAYSANDU":"FALSE","RIO_NEGRO":"FALSE","RIVERA":"FALSE","ROCHA":"FALSE","SALTO":"FALSE","SAN_JOSE":"FALSE","SORIANO":"FALSE","TACUAREMBO":"FALSE","TREINTA_Y_TRES":"FALSE","META_NINOS":"25.0%","META_EMBARAZADAS":"25.0%","META_ADOLESCENTE":"0.0%","META_ADULTO":"31.3%","META_ADULTO_MAYOR":"12.5%","MEDICAMENTOS_GENERAL":"150","MEDICAMENTOS_GENERAL_FONASA":"161","MEDICAMENTOS_TOPEADOS":"s/d","MEDICAMENTOS_TOPEADOS_FONASA":"s/d","CONSULTA_GENERAL":"s/d","CONSULTA_GENERAL_FONASA":"s/d","CONSULTA_PEDIATRIA":"s/d","CONSULTA_PEDIATRIA_FONASA":"s/d","CONTROL_EMBARAZO":"s/d","CONTROL_EMBARAZO_FONASA":"s/d","CONSULTA_GINECOLOGIA":"s/d","CONSULTA_GINECOLOGIA_FONASA":"s/d","CONSULT_OTR_ESP":"s/d","CONSULT_OTR_ESP_FONASA":"s/d","CONSULTA_NO_URG_DOM":"s/d","CONSULTA_NO_URG_DOM_FONASA":"s/d","CONS_ODONT":"s/d","CONS_ODONT_FONASA":"s/d","CONS_MED_REF":"s/d","CONS_MED_REF_FONASA":"s/d","CONS_URG_CENTRALIZADA":"s/d","CONS_URG_CENTRALIZADA_FONASA":"s/d","CONS_URG_DOM":"s/d","CONS_URG_DOM_FONASA":"s/d","ESTUDIO_ENDOSCOPIA":"s/d","ESTUDIO_ENDOSCOPIA_FONASA":"s/d","ESTUDIO_ECOGRAFIA_SIMPLE":"s/d","ESTUDIO_ECOGRAFIA_SIMPLE_FONASA":"s/d","ESTUDIO_ECOGRAFIA_OBS":"s/d","ESTUDIO_ECOGRAFIA_OBS_FONASA":"s/d","ESTUDIO_ECODOPPLER":"s/d","ESTUDIO_ECODOPPLER_FONASA":"s/d","ESTUDIO_IMAGEN_ABDOMEN":"s/d","ESTUDIO_IMAGEN_ABDOMEN_FONASA":"s/d","ESTUDIO_IMAGEN_TORAX":"s/d","ESTUDIO_IMAGEN_TORAX_FONASA":"s/d","ESTUDIO_IMAGEN_COLORECTAL":"s/d","ESTUDIO_IMAGEN_COLORECTAL_FONASA":"s/d","ESTUDIO_RESONANCIA":"s/d","ESTUDIO_RESONANCIA_FONASA":"s/d","ESTUDIO_TOMOGRAFIA":"s/d","ESTUDIO_TOMOGRAFIA_FONASA":"s/d","ESTUDIO_LABORATORIO":"s/d","ESTUDIO_LABORATORIO_FONASA":"s/d","TIEMPO_ESP_MED_GEN":"s/d","TIEMPO_ESP_PEDIATRIA":"s/d","TIEMPO_ESP_CIRUG":"s/d","TIEMPO_ESP_GIN":"s/d","ENT_QUEJAS":"s/d","ENT_DERECHOS":"s/d","PERSONAL_CANT_MED":"s/d","PERSONAL_CANT_GIN":"s/d","PERSONAL_CANT_PED":"s/d","PERSONAL_CANT_ENF":"s/d","PERSONAL_CANT_LICENF":"s/d","CITAS_PERSONAL":"TRUE","CITAS_TELEFONICA":"TRUE","CITAS_WEB":"TRUE","RECORDATORIO_TELEFONO":"FALSE","RECORDATORIO_SMS":"FALSE","RECORDATORIO_CORREO":"FALSE","INCOMPLETA":"TRUE","COSTO":{"MEDICAMENTOS":"s/d","CONSULTAS_NO_URGENTES":"s/d","CONSULTAS_URGENTES":"s/d","ESTUDIOS_Y_LABORATORIOS":"s/d"},"METAS":{"NINOS":"25.0%","EMBARAZADAS":"25.0%","ADOLESCENTE":"0.0%","ADULTO":"31.3%","ADULTO_MAYOR":"12.5%"},"TIEMPOS_ESPERA":{"MEDICINA_GENERAL":"s/d","PEDIATRIA":"s/d","CIRUGIA_GENERAL":"s/d","GINECOLOGIA":"s/d"},"SATISFACCION":{"QUEJAS":"s/d","DERECHOS":"s/d"},"PERSONAL":{"MEDICOS":"s/d","GINECOLOGOS":"s/d","PEDIATRAS":"s/d","ENFERMEROS":"s/d","LICENFER":"s/d"}},{"NOMBRE":"SMI - Servicio Médico Integral ","WEB":"http://www.serviciomedicointegral.com.uy","ARTIGAS":"FALSE","CANELONES":"FALSE","CERRO_LARGO":"FALSE","COLONIA":"FALSE","DURAZNO":"FALSE","FLORES":"FALSE","FLORIDA":"FALSE","LAVALLEJA":"FALSE","MALDONADO":"FALSE","MONTEVIDEO":"TRUE","PAYSANDU":"FALSE","RIO_NEGRO":"FALSE","RIVERA":"FALSE","ROCHA":"FALSE","SALTO":"FALSE","SAN_JOSE":"FALSE","SORIANO":"FALSE","TACUAREMBO":"FALSE","TREINTA_Y_TRES":"FALSE","META_NINOS":"96.8%","META_EMBARAZADAS":"98.8%","META_ADOLESCENTE":"35.5%","META_ADULTO":"45.9%","META_ADULTO_MAYOR":"58.5%","MEDICAMENTOS_GENERAL":"170","MEDICAMENTOS_GENERAL_FONASA":"s/d","MEDICAMENTOS_TOPEADOS":"83","MEDICAMENTOS_TOPEADOS_FONASA":"83","CONSULTA_GENERAL":"81","CONSULTA_GENERAL_FONASA":"81","CONSULTA_PEDIATRIA":"0","CONSULTA_PEDIATRIA_FONASA":"0","CONTROL_EMBARAZO":"76","CONTROL_EMBARAZO_FONASA":"76","CONSULTA_GINECOLOGIA":"76","CONSULTA_GINECOLOGIA_FONASA":"76","CONSULT_OTR_ESP":"171","CONSULT_OTR_ESP_FONASA":"142","CONSULTA_NO_URG_DOM":"256","CONSULTA_NO_URG_DOM_FONASA":"0","CONS_ODONT":"234","CONS_ODONT_FONASA":"0","CONS_MED_REF":"0","CONS_MED_REF_FONASA":"0","CONS_URG_CENTRALIZADA":"76","CONS_URG_CENTRALIZADA_FONASA":"169","CONS_URG_DOM":"348","CONS_URG_DOM_FONASA":"0","ESTUDIO_ENDOSCOPIA":"335","ESTUDIO_ENDOSCOPIA_FONASA":"290","ESTUDIO_ECOGRAFIA_SIMPLE":"290","ESTUDIO_ECOGRAFIA_SIMPLE_FONASA":"259","ESTUDIO_ECOGRAFIA_OBS":"290","ESTUDIO_ECOGRAFIA_OBS_FONASA":"259","ESTUDIO_ECODOPPLER":"335","ESTUDIO_ECODOPPLER_FONASA":"290","ESTUDIO_IMAGEN_ABDOMEN":"237","ESTUDIO_IMAGEN_ABDOMEN_FONASA":"237","ESTUDIO_IMAGEN_TORAX":"237","ESTUDIO_IMAGEN_TORAX_FONASA":"237","ESTUDIO_IMAGEN_COLORECTAL":"237","ESTUDIO_IMAGEN_COLORECTAL_FONASA":"237","ESTUDIO_RESONANCIA":"1164","ESTUDIO_RESONANCIA_FONASA":"1164","ESTUDIO_TOMOGRAFIA":"1129","ESTUDIO_TOMOGRAFIA_FONASA":"1129","ESTUDIO_LABORATORIO":"473","ESTUDIO_LABORATORIO_FONASA":"473","TIEMPO_ESP_MED_GEN":"0","TIEMPO_ESP_PEDIATRIA":"0","TIEMPO_ESP_CIRUG":"0.25","TIEMPO_ESP_GIN":"0.02","ENT_QUEJAS":"59%","ENT_DERECHOS":"32%","PERSONAL_CANT_MED":"7,9","PERSONAL_CANT_GIN":"9,1","PERSONAL_CANT_PED":"20,5","PERSONAL_CANT_ENF":"2,9","PERSONAL_CANT_LICENF":"0","CITAS_PERSONAL":"TRUE","CITAS_TELEFONICA":"TRUE","CITAS_WEB":"TRUE","RECORDATORIO_TELEFONO":"FALSE","RECORDATORIO_SMS":"FALSE","RECORDATORIO_CORREO":"FALSE","INCOMPLETA":"TRUE","COSTO":{"MEDICAMENTOS":"s/d","CONSULTAS_NO_URGENTES":79,"CONSULTAS_URGENTES":148,"ESTUDIOS_Y_LABORATORIOS":387},"METAS":{"NINOS":"96.8%","EMBARAZADAS":"98.8%","ADOLESCENTE":"35.5%","ADULTO":"45.9%","ADULTO_MAYOR":"58.5%"},"TIEMPOS_ESPERA":{"MEDICINA_GENERAL":"0","PEDIATRIA":"0","CIRUGIA_GENERAL":"0.25","GINECOLOGIA":"0.02"},"SATISFACCION":{"QUEJAS":"59%","DERECHOS":"32%"},"PERSONAL":{"MEDICOS":"7,9","GINECOLOGOS":"9,1","PEDIATRAS":"20,5","ENFERMEROS":"2,9","LICENFER":"0"}},{"NOMBRE":"SUMMUM - Summum Medicina Privada S.A.","WEB":"http://www.summum.com.uy","ARTIGAS":"FALSE","CANELONES":"FALSE","CERRO_LARGO":"FALSE","COLONIA":"FALSE","DURAZNO":"FALSE","FLORES":"FALSE","FLORIDA":"FALSE","LAVALLEJA":"FALSE","MALDONADO":"FALSE","MONTEVIDEO":"TRUE","PAYSANDU":"FALSE","RIO_NEGRO":"FALSE","RIVERA":"FALSE","ROCHA":"FALSE","SALTO":"FALSE","SAN_JOSE":"FALSE","SORIANO":"FALSE","TACUAREMBO":"FALSE","TREINTA_Y_TRES":"FALSE","META_NINOS":"71.5%","META_EMBARAZADAS":"98.8%","META_ADOLESCENTE":"0.0%","META_ADULTO":"53.3%","META_ADULTO_MAYOR":"0.0%","MEDICAMENTOS_GENERAL":"150","MEDICAMENTOS_GENERAL_FONASA":"122","MEDICAMENTOS_TOPEADOS":"s/d","MEDICAMENTOS_TOPEADOS_FONASA":"s/d","CONSULTA_GENERAL":"s/d","CONSULTA_GENERAL_FONASA":"s/d","CONSULTA_PEDIATRIA":"s/d","CONSULTA_PEDIATRIA_FONASA":"s/d","CONTROL_EMBARAZO":"s/d","CONTROL_EMBARAZO_FONASA":"s/d","CONSULTA_GINECOLOGIA":"s/d","CONSULTA_GINECOLOGIA_FONASA":"s/d","CONSULT_OTR_ESP":"s/d","CONSULT_OTR_ESP_FONASA":"s/d","CONSULTA_NO_URG_DOM":"s/d","CONSULTA_NO_URG_DOM_FONASA":"s/d","CONS_ODONT":"s/d","CONS_ODONT_FONASA":"s/d","CONS_MED_REF":"s/d","CONS_MED_REF_FONASA":"s/d","CONS_URG_CENTRALIZADA":"s/d","CONS_URG_CENTRALIZADA_FONASA":"s/d","CONS_URG_DOM":"s/d","CONS_URG_DOM_FONASA":"s/d","ESTUDIO_ENDOSCOPIA":"s/d","ESTUDIO_ENDOSCOPIA_FONASA":"s/d","ESTUDIO_ECOGRAFIA_SIMPLE":"s/d","ESTUDIO_ECOGRAFIA_SIMPLE_FONASA":"s/d","ESTUDIO_ECOGRAFIA_OBS":"s/d","ESTUDIO_ECOGRAFIA_OBS_FONASA":"s/d","ESTUDIO_ECODOPPLER":"s/d","ESTUDIO_ECODOPPLER_FONASA":"s/d","ESTUDIO_IMAGEN_ABDOMEN":"s/d","ESTUDIO_IMAGEN_ABDOMEN_FONASA":"s/d","ESTUDIO_IMAGEN_TORAX":"s/d","ESTUDIO_IMAGEN_TORAX_FONASA":"s/d","ESTUDIO_IMAGEN_COLORECTAL":"s/d","ESTUDIO_IMAGEN_COLORECTAL_FONASA":"s/d","ESTUDIO_RESONANCIA":"s/d","ESTUDIO_RESONANCIA_FONASA":"s/d","ESTUDIO_TOMOGRAFIA":"s/d","ESTUDIO_TOMOGRAFIA_FONASA":"s/d","ESTUDIO_LABORATORIO":"s/d","ESTUDIO_LABORATORIO_FONASA":"s/d","TIEMPO_ESP_MED_GEN":"0.11","TIEMPO_ESP_PEDIATRIA":"0.1","TIEMPO_ESP_CIRUG":"0.53","TIEMPO_ESP_GIN":"1.02","ENT_QUEJAS":"79%","ENT_DERECHOS":"44%","PERSONAL_CANT_MED":"s/d","PERSONAL_CANT_GIN":"s/d","PERSONAL_CANT_PED":"s/d","PERSONAL_CANT_ENF":"s/d","PERSONAL_CANT_LICENF":"s/d","CITAS_PERSONAL":"TRUE","CITAS_TELEFONICA":"TRUE","CITAS_WEB":"TRUE","RECORDATORIO_TELEFONO":"FALSE","RECORDATORIO_SMS":"TRUE","RECORDATORIO_CORREO":"TRUE","INCOMPLETA":"TRUE","COSTO":{"MEDICAMENTOS":"s/d","CONSULTAS_NO_URGENTES":"s/d","CONSULTAS_URGENTES":"s/d","ESTUDIOS_Y_LABORATORIOS":"s/d"},"METAS":{"NINOS":"71.5%","EMBARAZADAS":"98.8%","ADOLESCENTE":"0.0%","ADULTO":"53.3%","ADULTO_MAYOR":"0.0%"},"TIEMPOS_ESPERA":{"MEDICINA_GENERAL":"0.11","PEDIATRIA":"0.1","CIRUGIA_GENERAL":"0.53","GINECOLOGIA":"1.02"},"SATISFACCION":{"QUEJAS":"79%","DERECHOS":"44%"},"PERSONAL":{"MEDICOS":"s/d","GINECOLOGOS":"s/d","PEDIATRAS":"s/d","ENFERMEROS":"s/d","LICENFER":"s/d"}},{"NOMBRE":"UNIVERSAL - Universal Sociedad de Producción Sanitaria","WEB":"http://www.sociedadmedicauniversal.com","ARTIGAS":"FALSE","CANELONES":"TRUE","CERRO_LARGO":"FALSE","COLONIA":"FALSE","DURAZNO":"FALSE","FLORES":"FALSE","FLORIDA":"FALSE","LAVALLEJA":"FALSE","MALDONADO":"FALSE","MONTEVIDEO":"TRUE","PAYSANDU":"FALSE","RIO_NEGRO":"FALSE","RIVERA":"FALSE","ROCHA":"FALSE","SALTO":"FALSE","SAN_JOSE":"TRUE","SORIANO":"FALSE","TACUAREMBO":"FALSE","TREINTA_Y_TRES":"FALSE","META_NINOS":"61.7%","META_EMBARAZADAS":"99.3%","META_ADOLESCENTE":"23.2%","META_ADULTO":"44.0%","META_ADULTO_MAYOR":"57.4%","MEDICAMENTOS_GENERAL":"144","MEDICAMENTOS_GENERAL_FONASA":"s/d","MEDICAMENTOS_TOPEADOS":"76","MEDICAMENTOS_TOPEADOS_FONASA":"76","CONSULTA_GENERAL":"75","CONSULTA_GENERAL_FONASA":"0","CONSULTA_PEDIATRIA":"0","CONSULTA_PEDIATRIA_FONASA":null,"CONTROL_EMBARAZO":"71","CONTROL_EMBARAZO_FONASA":"0","CONSULTA_GINECOLOGIA":"71","CONSULTA_GINECOLOGIA_FONASA":"0","CONSULT_OTR_ESP":null,"CONSULT_OTR_ESP_FONASA":null,"CONSULTA_NO_URG_DOM":"186","CONSULTA_NO_URG_DOM_FONASA":"126","CONS_ODONT":"104","CONS_ODONT_FONASA":"0","CONS_MED_REF":"75","CONS_MED_REF_FONASA":"0","CONS_URG_CENTRALIZADA":"71","CONS_URG_CENTRALIZADA_FONASA":"0","CONS_URG_DOM":"361","CONS_URG_DOM_FONASA":"180","ESTUDIO_ENDOSCOPIA":"255","ESTUDIO_ENDOSCOPIA_FONASA":"159","ESTUDIO_ECOGRAFIA_SIMPLE":"239","ESTUDIO_ECOGRAFIA_SIMPLE_FONASA":"151","ESTUDIO_ECOGRAFIA_OBS":"239","ESTUDIO_ECOGRAFIA_OBS_FONASA":"151","ESTUDIO_ECODOPPLER":"416","ESTUDIO_ECODOPPLER_FONASA":"240","ESTUDIO_IMAGEN_ABDOMEN":"239","ESTUDIO_IMAGEN_ABDOMEN_FONASA":"151","ESTUDIO_IMAGEN_TORAX":"238","ESTUDIO_IMAGEN_TORAX_FONASA":"151","ESTUDIO_IMAGEN_COLORECTAL":"384","ESTUDIO_IMAGEN_COLORECTAL_FONASA":"224","ESTUDIO_RESONANCIA":"384","ESTUDIO_RESONANCIA_FONASA":"224","ESTUDIO_TOMOGRAFIA":"384","ESTUDIO_TOMOGRAFIA_FONASA":"224","ESTUDIO_LABORATORIO":"521","ESTUDIO_LABORATORIO_FONASA":"326","TIEMPO_ESP_MED_GEN":"0.01","TIEMPO_ESP_PEDIATRIA":"0.01","TIEMPO_ESP_CIRUG":"0.33","TIEMPO_ESP_GIN":"0.08","ENT_QUEJAS":"57%","ENT_DERECHOS":"32%","PERSONAL_CANT_MED":"13,5","PERSONAL_CANT_GIN":"8,3","PERSONAL_CANT_PED":"14,1","PERSONAL_CANT_ENF":"5,9","PERSONAL_CANT_LICENF":"0,4","CITAS_PERSONAL":"TRUE","CITAS_TELEFONICA":"TRUE","CITAS_WEB":"FALSE","RECORDATORIO_TELEFONO":"FALSE","RECORDATORIO_SMS":"FALSE","RECORDATORIO_CORREO":"FALSE","INCOMPLETA":"TRUE","COSTO":{"MEDICAMENTOS":"s/d","CONSULTAS_NO_URGENTES":44,"CONSULTAS_URGENTES":153,"ESTUDIOS_Y_LABORATORIOS":220},"METAS":{"NINOS":"61.7%","EMBARAZADAS":"99.3%","ADOLESCENTE":"23.2%","ADULTO":"44.0%","ADULTO_MAYOR":"57.4%"},"TIEMPOS_ESPERA":{"MEDICINA_GENERAL":"0.01","PEDIATRIA":"0.01","CIRUGIA_GENERAL":"0.33","GINECOLOGIA":"0.08"},"SATISFACCION":{"QUEJAS":"57%","DERECHOS":"32%"},"PERSONAL":{"MEDICOS":"13,5","GINECOLOGOS":"8,3","PEDIATRAS":"14,1","ENFERMEROS":"5,9","LICENFER":"0,4"}}]